amr.py
simplesmatch.py
simplesmatchscore.py
smatch.py
simple_smatch-0.1.3.1.data/scripts/simplesmatch.py
simple_smatch-0.1.3.1.data/scripts/simplesmatchscore.py
simple_smatch-0.1.3.1.data/scripts/smatch.py
simple_smatch-0.1.3.1.dist-info/LICENSE.txt
simple_smatch-0.1.3.1.dist-info/METADATA
simple_smatch-0.1.3.1.dist-info/WHEEL
simple_smatch-0.1.3.1.dist-info/top_level.txt
simple_smatch-0.1.3.1.dist-info/RECORD
